cursedpy/__init__.py
cursedpy/cursed.py
cursedpy/http/__init__.py
cursedpy/http/abc.py
cursedpy/http/aiohttp_client.py
cursedpy/http/cursed_client.py
cursedpy/types.py
cursedpy-0.2.0.dist-info/METADATA
cursedpy-0.2.0.dist-info/WHEEL
cursedpy-0.2.0.dist-info/RECORD
