Metadata-Version: 2.1
Name: cursedpy
Version: 0.2.0
Summary: Dead simple Curseforge API wrapper
Author: Coffeemeow
Author-email: coffeemeowgirl@gmail.com
Requires-Python: >=3.12,<4.0
Classifier: Programming Language :: Python :: 3
Classifier: Programming Language :: Python :: 3.12
Requires-Dist: aiohttp (>=3.9.5,<4.0.0)
Requires-Dist: colorama (>=0.4.6,<0.5.0)
Requires-Dist: dataclass-wizard (>=0.22.3,<0.23.0)
Requires-Dist: requests (>=2.31.0,<3.0.0)
